[
  {
    "type": "instagram",
    "product": "Sunset Projection Lamp",
    "content": {
      "caption": "This Sunset Projection Lamp > everything else\n\nSave this for later! Link in bio \ud83d\uded2",
      "hashtags": "#smarthome #aesthetic #musthaves #shopnow #trending",
      "best_time": "12:00 PM or 9:00 PM"
    },
    "generated_at": "2025-12-14T08:13:38.499872",
    "scheduled_for": "2025-12-14T12:13:38.499875"
  },
  {
    "type": "tiktok",
    "product": "LED Strip Lights RGB",
    "content": {
      "hook": "This LED Strip Lights RGB is going VIRAL for a reason",
      "caption": "This LED Strip Lights RGB is going VIRAL for a reason\n\nLink in bio to get yours!\n\n#fyp #viral #tiktokfinds #amazonfinds #musthaves #trending",
      "suggested_sound": "trending sound - aesthetic vibes",
      "best_time": "8:00 PM"
    },
    "generated_at": "2025-12-14T08:13:38.499886",
    "scheduled_for": "2025-12-15T03:13:38.499887"
  },
  {
    "type": "instagram",
    "product": "LED Therapy Mask",
    "content": {
      "caption": "This LED Therapy Mask > everything else\n\nSave this for later! Link in bio \ud83d\uded2",
      "hashtags": "#beautytools #aesthetic #musthaves #shopnow #trending",
      "best_time": "13:00 PM or 8:00 PM"
    },
    "generated_at": "2025-12-14T08:13:38.499899",
    "scheduled_for": "2025-12-14T17:13:38.499900"
  }
]